setup.py
django_encrypted_fields_python3.egg-info/PKG-INFO
django_encrypted_fields_python3.egg-info/SOURCES.txt
django_encrypted_fields_python3.egg-info/dependency_links.txt
django_encrypted_fields_python3.egg-info/requires.txt
django_encrypted_fields_python3.egg-info/top_level.txt
encrypted_fields/__init__.py
encrypted_fields/fields.py
encrypted_fields/models.py
encrypted_fields/tests.py