Metadata-Version: 1.0
Name: django-encrypted-fields-python3
Version: 1.1.3
Summary: This is a collection of Django Model Field classes that are encrypted using Keyczar.
Home-page: http://github.com/defrex/django-encrypted-fields/
Author: Aron Jones
Author-email: aron.jones@gmail.com
License: BSD
Platform: UNKNOWN
